psltdsim/__init__.py
psltdsim/init_PSLF.py
psltdsim/runSimPY3.py
psltdsim/runSim_IPY.py
psltdsim/runSim_OG.py
psltdsim/BAAgents/BA.py
psltdsim/BAAgents/TLB.py
psltdsim/BAAgents/__init__.py
psltdsim/agc/__init__.py
psltdsim/agc/distACE.py
psltdsim/amqp/AMQPAgent.py
psltdsim/amqp/IPY_init.py
psltdsim/amqp/PY3importMir.py
psltdsim/amqp/__init__.py
psltdsim/amqp/agentUpdate.py
psltdsim/amqp/clearQ.py
psltdsim/amqp/endSim.py
psltdsim/amqp/handoff.py
psltdsim/amqp/sysCrash.py
psltdsim/data/__init__.py
psltdsim/data/exportDict.py
psltdsim/data/exportMat.py
psltdsim/data/getDateStr.py
psltdsim/data/getTimeStr.py
psltdsim/data/loadMirrorDictionary.py
psltdsim/data/makeMat.py
psltdsim/data/makeMirrorDictionary.py
psltdsim/data/mergeDicts.py
psltdsim/data/readMirror.py
psltdsim/data/saveMirror.py
psltdsim/data/saveMirrorDictionary.py
psltdsim/data/single2float.py
psltdsim/dynamicAgents/__init__.py
psltdsim/dynamicAgents/genericGasGovAgent.py
psltdsim/dynamicAgents/genericHydroGovAgent.py
psltdsim/dynamicAgents/genericSteamGovAgent.py
psltdsim/dynamicAgents/ggov1Agent.py
psltdsim/dynamicAgents/pgov1Agent.py
psltdsim/dynamicAgents/tgov1Agent.py
psltdsim/filterAgents/PIAgent.py
psltdsim/filterAgents/__init__.py
psltdsim/filterAgents/deadBandAgent.py
psltdsim/filterAgents/integratorAgent.py
psltdsim/filterAgents/lowPassAgent.py
psltdsim/find/__init__.py
psltdsim/find/findAgent.py
psltdsim/find/findArea.py
psltdsim/find/findBranchByScanBusCk.py
psltdsim/find/findBranchByTFC.py
psltdsim/find/findBus.py
psltdsim/find/findGenOnBus.py
psltdsim/find/findLoadOnBus.py
psltdsim/find/findPowerPlant.py
psltdsim/find/findShuntOnBus.py
psltdsim/find/makeBranchDict.py
psltdsim/find/makeBusSearchDict.py
psltdsim/math/__init__.py
psltdsim/math/pdif.py
psltdsim/mirror/LTD_SolveCase.py
psltdsim/mirror/Mirror.py
psltdsim/mirror/__init__.py
psltdsim/mirror/combinedSwing.py
psltdsim/mirror/createPY3DynamicAgents.py
psltdsim/mirror/create_mirror_agents.py
psltdsim/mirror/distPacc.py
PSLTDSim-0.1.0.dist-info/LICENSE.txt
PSLTDSim-0.1.0.dist-info/METADATA
PSLTDSim-0.1.0.dist-info/WHEEL
PSLTDSim-0.1.0.dist-info/top_level.txt
PSLTDSim-0.1.0.dist-info/RECORD
