Metadata-Version: 2.1
Name: PSLTDSim
Version: 0.1.0
Summary: Power System Long-Term Dynamic Simulator
Home-page: https://github.com/thadhaines/PSLTDSim
Author: Thad Haines
Author-email: jhaines@mtech.edu
License: UNKNOWN
Platform: UNKNOWN
Classifier: Programming Language :: Python :: 3
Classifier: License :: OSI Approved :: MIT License
Classifier: Operating System :: OS Independent
Requires-Python: >=3.6
